pythia/__init__.py
pythia/__main__.py
pythia/applications/__init__.py
pythia/applications/annotation.py
pythia/applications/base.py
pythia/applications/command_line.py
pythia/applications/demo.py
pythia/cli/__init__.py
pythia/cli/app.py
pythia/config.py
pythia/event_stream/__init__.py
pythia/event_stream/base.py
pythia/event_stream/kafka.py
pythia/event_stream/log.py
pythia/event_stream/memory.py
pythia/event_stream/redis.py
pythia/exceptions.py
pythia/iterators.py
pythia/models/__init__.py
pythia/models/base.py
pythia/paths.py
pythia/pipelines/__init__.py
pythia/pipelines/base.py
pythia/types.py
pythia/utils/__init__.py
pythia/utils/ds.py
pythia/utils/ext.py
pythia/utils/gst.py
pythia/utils/maskrcnn.py
pythia/utils/message_handlers.py
pythia/utils/str2pythia.py
pythia/version.py
pythiags-1.3.0.dist-info/entry_points.txt
pythiags-1.3.0.dist-info/WHEEL
pythiags-1.3.0.dist-info/METADATA
pythiags-1.3.0.dist-info/RECORD
