Metadata-Version: 2.1
Name: pythiags
Version: 1.3.0
Summary: pythonic Deepstream.
Home-page: https://dev.rmclabs.io/pythia
Author: Pablo Woolvett
Author-email: pablowoolvett@gmail.com
Requires-Python: >=3.8,<4.0
Classifier: Programming Language :: Python :: 3
Classifier: Programming Language :: Python :: 3.8
Classifier: Programming Language :: Python :: 3.9
Classifier: Programming Language :: Python :: 3.10
Provides-Extra: cli
Provides-Extra: jinja
Provides-Extra: kafka
Provides-Extra: opencv
Provides-Extra: redis
Requires-Dist: Jinja2 (>=3.1.2,<4.0.0); extra == "jinja"
Requires-Dist: fire (==0.4.0); extra == "cli"
Requires-Dist: kafka-python (==2.0.2); extra == "kafka"
Requires-Dist: numpy (>=1.23.2,<2.0.0)
Requires-Dist: opencv-python (>=4.6.0.66); extra == "opencv"
Requires-Dist: pycairo (==1.21.0)
Requires-Dist: pyds_ext (>=2,<3)
Requires-Dist: pygobject (==3.36.0)
Requires-Dist: redis (==4.3.4); extra == "redis"
Requires-Dist: typer; extra == "cli"
Project-URL: Bug Tracker, https://github.com/rmclabs-io/pythia/issues
Project-URL: Documentation, https://rmclabs-io.github.io/pythia-docs/
Project-URL: Repository, https://github.com/rmclabs-io/pythia
